aiopulse/__init__.py
aiopulse/const.py
aiopulse/errors.py
aiopulse/hub.py
aiopulse/roller.py
aiopulse/room.py
aiopulse/scene.py
aiopulse/timer.py
aiopulse/transport.py
aiopulse/utils.py
aiopulse-0.4.6.dist-info/METADATA
aiopulse-0.4.6.dist-info/WHEEL
aiopulse-0.4.6.dist-info/licenses/LICENSE
aiopulse-0.4.6.dist-info/RECORD
