Metadata-Version: 2.3
Name: aiopulse
Version: 0.4.6
Summary: Asynchronous library to control Rollease Acmeda Automate roller blinds via a version 1 Pulse Hub.
Project-URL: Homepage, https://github.com/atmurray/aiopulse
Project-URL: Issues, https://github.com/atmurray/aiopulse/issues
Author-email: Alan Murray <pypi@atmurray.net>
License:                                  Apache License
License-File: LICENSE
Classifier: Development Status :: 4 - Beta
Classifier: Intended Audience :: Developers
Classifier: License :: OSI Approved :: Apache Software License
Classifier: Operating System :: OS Independent
Classifier: Programming Language :: Python :: 3
Classifier: Topic :: Software Development :: Libraries :: Python Modules
Requires-Python: >=3.4
